partial_date/__init__.py
partial_date/fields.py
partial_date/tests.py
django_partial_date-1.3.2.dist-info/LICENSE
django_partial_date-1.3.2.dist-info/METADATA
django_partial_date-1.3.2.dist-info/WHEEL
django_partial_date-1.3.2.dist-info/top_level.txt
django_partial_date-1.3.2.dist-info/RECORD
