Metadata-Version: 2.1
Name: django-partial-date
Version: 1.3.2
Summary: Django custom model field for partial dates with the form YYYY, YYYY-MM, YYYY-MM-DD
Home-page: https://github.com/ktowen/django_partial_date
Author: ktowen
Author-email: towenpa@gmail.com
License: MIT
Keywords: fields,django,dates,partial
Platform: UNKNOWN
Classifier: Development Status :: 5 - Production/Stable
Classifier: Framework :: Django
Classifier: Intended Audience :: Developers
Classifier: License :: OSI Approved :: MIT License
